MANIFEST.in
README.md
requirements.txt
setup.py
tm_lib.egg-info/PKG-INFO
tm_lib.egg-info/SOURCES.txt
tm_lib.egg-info/dependency_links.txt
tm_lib.egg-info/requires.txt
tm_lib.egg-info/top_level.txt
tmlib/__init__.py
tmlib/checkin.py
tmlib/customer.py
tmlib/eiutils.py
tmlib/generate_key.py
tmlib/lt_updates.py
tmlib/migrations.py
tmlib/models.py
tmlib/rego_key.py
tmlib/settings.py
tmlib/tm_authorisation.py
tmlib/tm_db.py
tmlib/tm_obfuscate.py
tmlib/tradelogs.py
tmlib/tradingminion.py