Metadata-Version: 2.1
Name: tm-lib
Version: 0.2.0
Summary: A lib for the tm projects
Home-page: https://gitlab.com/trading-minions/prototypes/tmlib
Author: Michael Smith
Author-email: mike@tradingminions.com
License: UNKNOWN
Keywords: tmlib
Platform: UNKNOWN
Classifier: Development Status :: 3 - Alpha
Classifier: Programming Language :: Python :: 3.6
Classifier: Programming Language :: Python :: 3.7
Provides-Extra: test
Provides-Extra: dev
